Metadata-Version: 2.1
Name: python-dialpad-httpx
Version: 1.1.0
Summary: A python wrapper for the Dialpad REST API
Home-page: https://github.com/dialpad/dialpad-python-sdk
Author: Jake Nielsen
Author-email: jnielsen@dialpad.com
License: MIT
License-File: LICENSE
Requires-Dist: cached-property
Requires-Dist: certifi
Requires-Dist: chardet
Requires-Dist: idna
Requires-Dist: httpx
Requires-Dist: urllib3
